[
  {
    "cqName": "TC_DemoPrj_7",
    "cqId": 7,
    "almName": "TC_DemoPrj_7",
    "almId": 2281,
    "digest": "f885c1b1fff58aa3e4e1d388e53bfefdc0d52797"
  },
  {
    "cqName": "TC_DemoPrj_8",
    "cqId": 8,
    "almName": "TC_DemoPrj_8",
    "almId": 2282,
    "digest": "18e6cb7c04d994f4ae2ed3dd5456558322d6f212"
  },
  {
    "cqName": "TC_DemoPrj_9",
    "cqId": 9,
    "almName": "TC_DemoPrj_9",
    "almId": 2283,
    "digest": "61984b73609de006b28061c040af897e7600e7aa"
  },
  {
    "cqName": "TC_DemoPrj_10",
    "cqId": 10,
    "almName": "TC_DemoPrj_10",
    "almId": 2284,
    "digest": "bc9e8d47d8269e829f4b2ba968e8003349e59e5b"
  }
]